{
  "bounty_hunter_shuriken_toss": {
    "behavior": [
      "UNIT_TARGET"
    ],
    "targetTeam": "ENEMY",
    "targetType": [
      "HERO",
      "BASIC"
    ],
    "damageType": "MAGICAL",
    "castRange": 0,
    "cooldown": [
      5
    ],
    "manaCost": [
      75,
      80,
      85,
      90
    ],
    "effects": {
      "bonus_damage": [
        100,
        170,
        240,
        310
      ],
      "speed": [
        1000,
        1000,
        1000,
        1000
      ],
      "bounce_aoe": 1200,
      "slow_duration": 0.35,
      "cast_range": [
        375,
        425,
        475,
        525
      ],
      "slow": 100,
      "AbilityCastRange": [
        375,
        425,
        475,
        525
      ]
    }
  },
  "bounty_hunter_jinada": {
    "behavior": [
      "UNIT_TARGET",
      "AUTOCAST",
      "ATTACK"
    ],
    "targetTeam": "ENEMY",
    "targetType": [
      "HERO",
      "BASIC",
      "BUILDING"
    ],
    "damageType": "PHYSICAL",
    "castRange": 150,
    "cooldown": [],
    "manaCost": [],
    "effects": {
      "bonus_damage": [
        70,
        105,
        140,
        175
      ],
      "gold_steal": [
        12,
        20,
        28,
        36
      ],
      "AbilityCooldown": [
        9,
        7,
        5,
        3
      ]
    }
  },
  "bounty_hunter_wind_walk": {
    "behavior": [
      "NO_TARGET",
      "IMMEDIATE",
      "IGNORE_CHANNEL"
    ],
    "targetType": [],
    "castRange": 0,
    "cooldown": [],
    "manaCost": [
      50
    ],
    "stealth": true,
    "fade_delay": 0,
    "effects": {
      "duration": [
        20,
        25,
        30,
        35
      ],
      "fade_time": [
        1,
        0.75,
        0.5,
        0.25
      ],
      "stun_duration": [
        1,
        1.2,
        1.4,
        1.6
      ],
      "AbilityCooldown": [
        18,
        17,
        16,
        15
      ],
      "damage_reduction_pct": 0
    }
  },
  "bounty_hunter_wind_walk_ally": {
    "behavior": [
      "UNIT_TARGET",
      "IMMEDIATE",
      "IGNORE_CHANNEL",
      "NOT_LEARNABLE"
    ],
    "targetTeam": "FRIENDLY",
    "targetType": [
      "HERO"
    ],
    "castRange": 650,
    "cooldown": [
      15
    ],
    "manaCost": [
      50
    ],
    "effects": {
      "fade_time": 0.5
    }
  },
  "bounty_hunter_track": {
    "behavior": [
      "UNIT_TARGET"
    ],
    "targetTeam": "ENEMY",
    "targetType": [
      "HERO"
    ],
    "castRange": 1000,
    "cooldown": [
      6,
      5,
      4
    ],
    "manaCost": [
      60
    ],
    "single_target": true,
    "vision_on_target": true,
    "effects": {
      "target_damage_amp": [
        8,
        12,
        16
      ],
      "bonus_damage_pct": [
        20,
        30,
        40
      ],
      "bonus_gold_self": [
        130,
        225,
        320
      ],
      "bonus_gold": [
        50,
        90,
        130
      ],
      "duration": 25,
      "gold_steal": [
        0.3,
        0.4,
        0.5
      ],
      "bonus_move_speed_pct": [
        12,
        16,
        20
      ]
    }
  },
  "bounty_hunter_lookout": {
    "behavior": [
      "POINT",
      "IGNORE_BACKSWING"
    ],
    "targetType": [],
    "castRange": 1800,
    "cooldown": [
      18
    ],
    "manaCost": [
      30
    ],
    "effects": {
      "max_lookouts": 4,
      "lookout_fade_time": 2.25,
      "radius": 150
    }
  },
  "bounty_hunter_cutpurse": {
    "behavior": [
      "PASSIVE",
      "HIDDEN"
    ],
    "targetType": [],
    "castRange": 0,
    "cooldown": [],
    "manaCost": [],
    "effects": {
      "gold_steal": [
        4,
        11,
        18,
        25
      ]
    }
  },
  "bounty_hunter_big_game_hunter": {
    "behavior": [
      "PASSIVE",
      "INNATE_UI"
    ],
    "targetType": [],
    "castRange": 0,
    "cooldown": [],
    "manaCost": [],
    "effects": {
      "bonus_killstreak_bounty": 20
    }
  }
}
